[
  {
    "fname": "akriti",
    "lname": "stha"
  },
  {
    "fname": "anuska",
    "lname": "stha"
  },
  {
    "fname": "Postman",
    "lname": "chetri"
  },
  {
    "fname": "ram",
    "lname": "stha"
  },
  {
    "fname": "lara",
    "lname": "achraya"
  },
  {
    "fname": "bombardino",
    "lname": "crocodilo"
  },
  {
    "fname": "tungtungtung",
    "lname": "sahur"
  },
  {
    "fname": "Muna",
    "lname": "madan"
  },
  {
    "fname": "Muna",
    "lname": "achraya"
  },
  {
    "fname": "Muna",
    "lname": "achraya"
  },
  {
    "fname": "Mun",
    "lname": "achraya"
  },
  {
    "fname": "Postman",
    "lname": "chetri"
  },
  {
    "fname": "john",
    "lname": "man"
  },
  {
    "fname": "john",
    "lname": "man"
  },
  {
    "fname": "Rajesh",
    "lname": "Hamal"
  }
]